assistmodeloregre/__init__.py
assistmodeloregre/modeloExtraTress.py
assistmodeloregre-0.1.dist-info/METADATA
assistmodeloregre-0.1.dist-info/WHEEL
assistmodeloregre-0.1.dist-info/top_level.txt
assistmodeloregre-0.1.dist-info/RECORD
